{
  "server": {
    "network": "tcp",
    "protocol": "http",
    "host": "localhost",
    "port": 3000
  },
  "dir": {
    "path": "/Users/vladislavpereskokov/Desktop/"
  },
  "status": [
    {
      "code": 200,
      "message": "Ok"
    },
    {
      "code": 400,
      "message": "Bad request"
    },
    {
      "code": 403,
      "message": "Forbidden"
    },
    {
      "code": 404,
      "message": "Not found"
    },
    {
      "code": 405,
      "message": "Method not allowed"
    }
  ],
  "http_methods": [
    {
      "type": "GET"
    },
    {
      "type": "HEAD"
    }
  ],
  "content_type": [
    {
      "expansion": ".css",
      "type": "text/css"
    }
  ]
}
